LICENSE
README.md
setup.cfg
setup.py
commonn_abs_lyr.egg-info/PKG-INFO
commonn_abs_lyr.egg-info/SOURCES.txt
commonn_abs_lyr.egg-info/dependency_links.txt
commonn_abs_lyr.egg-info/requires.txt
commonn_abs_lyr.egg-info/top_level.txt
connlayer/__init__.py
connlayer/cast_config.py
connlayer/clickhouse_client.py
connlayer/connection_interface.py
connlayer/constants.py
connlayer/cosmos_client.py
connlayer/mysql_client.py
connlayer/postgre_sql_client.py
connlayer/redis_client.py
connlayer/redis_connection_pool.py
connlayer/test_client.py
connlayer/validate_config.py